subprocessed/__init__.py
subprocessed/subprocessed.py
subprocessed-0.0.dist-info/LICENSE
subprocessed-0.0.dist-info/METADATA
subprocessed-0.0.dist-info/WHEEL
subprocessed-0.0.dist-info/top_level.txt
subprocessed-0.0.dist-info/RECORD
