Metadata-Version: 2.1
Name: subprocessed
Version: 0.0
Summary: Execute a function in a Python subprocess instead of using the Python main process.
Author-email: Yohann Pipeau <yohann.pipeau@gmail.com>
Project-URL: Homepage, https://github.com/gorgh/subprocessed
Project-URL: Bug Tracker, https://github.com/gorgh/subprocessed/issues
Classifier: Programming Language :: Python :: 3
Classifier: License :: OSI Approved :: MIT License
Classifier: Operating System :: POSIX
Requires-Python: >=3.7
License-File: LICENSE
Provides-Extra: build
Requires-Dist: build; extra == "build"
Provides-Extra: dev
Requires-Dist: tox>=4; extra == "dev"
Requires-Dist: subprocessed[build,format,lint,test,type]; extra == "dev"
Provides-Extra: format
Requires-Dist: isort; extra == "format"
Requires-Dist: black==23.*; extra == "format"
Provides-Extra: lint
Requires-Dist: pytest>=6; extra == "lint"
Requires-Dist: pylint>=2; extra == "lint"
Requires-Dist: pydocstyle>=2; extra == "lint"
Provides-Extra: test
Requires-Dist: pytest>=6; extra == "test"
Requires-Dist: coverage>=5.3; extra == "test"
Requires-Dist: pytest-cov; extra == "test"
Requires-Dist: pytest-profiling; extra == "test"
Provides-Extra: type
Requires-Dist: pytest>=6; extra == "type"
Requires-Dist: mypy; extra == "type"
